{
  "MeshCube|2022-01-08T15:27:19.926Z|11492": {
    "ƒ.MeshCube": {
      "idResource": "MeshCube|2022-01-08T15:27:19.926Z|11492",
      "name": "MeshCube",
      "type": "MeshCube"
    }
  },
  "Material|2022-01-08T15:28:39.028Z|46109": {
    "ƒ.Material": {
      "name": "GroundMaterial",
      "idResource": "Material|2022-01-08T15:28:39.028Z|46109",
      "shader": "ShaderTexture",
      "coat": {
        "ƒ.CoatTextured": {
          "color": "[1, 1, 1, 1]",
          "idTexture": "TextureImage|2022-01-08T15:57:06.095Z|59238"
        }
      }
    }
  },
  "TextureImage|2022-01-08T15:57:06.095Z|59238": {
    "ƒ.TextureImage": {
      "url": "Textures\\Terrain\\rocks.jpg",
      "type": "TextureImage",
      "Texture": {
        "idResource": "TextureImage|2022-01-08T15:57:06.095Z|59238",
        "name": "Textures\\Terrain\\rocks.jpg",
        "mipmap": "CRISP"
      }
    }
  },
  "TextureImage|2022-01-08T16:02:46.414Z|97543": {
    "ƒ.TextureImage": {
      "url": "Textures\\Terrain\\ground.jpg",
      "type": "TextureImage",
      "Texture": {
        "idResource": "TextureImage|2022-01-08T16:02:46.414Z|97543",
        "name": "Textures\\Terrain\\ground.jpg",
        "mipmap": "BLURRY"
      }
    }
  },
  "MeshCube|2022-02-13T09:02:24.853Z|43448": {
    "ƒ.MeshCube": {
      "idResource": "MeshCube|2022-02-13T09:02:24.853Z|43448",
      "name": "ObstacleCube",
      "type": "MeshCube"
    }
  },
  "Material|2022-02-13T09:02:43.900Z|50505": {
    "ƒ.Material": {
      "name": "ObstacleCubeMaterial",
      "idResource": "Material|2022-02-13T09:02:43.900Z|50505",
      "shader": "ShaderTexture",
      "coat": {
        "ƒ.CoatTextured": {
          "color": "[1, 1, 1, 1]",
          "idTexture": "TextureImage|2022-01-08T16:02:46.414Z|97543"
        }
      }
    }
  },
  "MeshCube|2022-02-13T10:13:57.579Z|88727": {
    "ƒ.MeshCube": {
      "idResource": "MeshCube|2022-02-13T10:13:57.579Z|88727",
      "name": "Border",
      "type": "MeshCube"
    }
  },
  "Material|2022-02-13T10:14:56.909Z|82707": {
    "ƒ.Material": {
      "name": "UniColorMaterial",
      "idResource": "Material|2022-02-13T10:14:56.909Z|82707",
      "shader": "ShaderUniColor",
      "coat": {
        "ƒ.CoatColored": {
          "color": "[1, 1, 1, 1]"
        }
      }
    }
  },
  "Graph|2022-01-08T12:51:22.101Z|15244": {
    "ƒ.Graph": {
      "name": "Graph",
      "components": {},
      "children": [
        {
          "ƒ.Node": {
            "name": "Level",
            "components": {},
            "children": [
              {
                "ƒ.Node": {
                  "name": "Characters",
                  "components": {},
                  "children": [
                    {
                      "ƒ.Node": {
                        "name": "Player",
                        "components": {},
                        "children": []
                      }
                    },
                    {
                      "ƒ.Node": {
                        "name": "NPC",
                        "components": {},
                        "children": []
                      }
                    }
                  ]
                }
              },
              {
                "ƒ.Node": {
                  "name": "Surroundings",
                  "components": {},
                  "children": [
                    {
                      "ƒ.Node": {
                        "name": "Background",
                        "components": {},
                        "children": []
                      }
                    },
                    {
                      "ƒ.Node": {
                        "name": "Foreground",
                        "components": {},
                        "children": [
                          {
                            "ƒ.Node": {
                              "name": "Movables",
                              "components": {},
                              "children": [
                                {
                                  "ƒ.Node": {
                                    "name": "Controllables",
                                    "components": {},
                                    "children": [
                                      {
                                        "ƒ.Node": {
                                          "name": "Obstacle1",
                                          "components": {
                                            "ComponentMesh": [
                                              {
                                                "ƒ.ComponentMesh": {
                                                  "idMesh": "MeshCube|2022-02-13T09:02:24.853Z|43448",
                                                  "pivot": {
                                                    "translation": "[0, 0, 0]",
                                                    "rotation": "[0, 0, 0]",
                                                    "scaling": "[2, 1, 1]"
                                                  },
                                                  "Component": {
                                                    "active": true
                                                  }
                                                }
                                              }
                                            ],
                                            "ComponentMaterial": [
                                              {
                                                "ƒ.ComponentMaterial": {
                                                  "sortForAlpha": false,
                                                  "clrPrimary": "[1, 1, 1, 1]",
                                                  "clrSecondary": "[1, 1, 1, 1]",
                                                  "pivot": {
                                                    "translation": "[0, 0]",
                                                    "rotation": 0,
                                                    "scaling": "[1, 1]"
                                                  },
                                                  "Component": {
                                                    "active": true
                                                  },
                                                  "idMaterial": "Material|2022-02-13T09:02:43.900Z|50505"
                                                }
                                              }
                                            ],
                                            "ComponentTransform": [
                                              {
                                                "ƒ.ComponentTransform": {
                                                  "local": {
                                                    "translation": "[0, 2, 0]",
                                                    "rotation": "[0, 0, 0]",
                                                    "scaling": "[0.5, 0.5, 0.5]"
                                                  },
                                                  "Component": {
                                                    "active": true
                                                  }
                                                }
                                              }
                                            ],
                                            "ComponentRigidbody": [
                                              {
                                                "ƒ.ComponentRigidbody": {
                                                  "initialization": "TO_PIVOT",
                                                  "friction": 0.2,
                                                  "restitution": 0.2,
                                                  "mass": 1,
                                                  "dampTranslation": 0.1,
                                                  "dampRotation": 0.1,
                                                  "effectGravity": 1,
                                                  "typeBody": "DYNAMIC",
                                                  "typeCollider": "CUBE",
                                                  "isTrigger": false,
                                                  "id": 1,
                                                  "pivot": {
                                                    "translation": "[0, 0, 0]",
                                                    "rotation": "[0, 0, 0]",
                                                    "scaling": "[1, 1, 1]"
                                                  },
                                                  "Component": {
                                                    "active": true
                                                  }
                                                }
                                              }
                                            ]
                                          },
                                          "children": []
                                        }
                                      },
                                      {
                                        "ƒ.Node": {
                                          "name": "Obstacle2",
                                          "components": {
                                            "ComponentMesh": [
                                              {
                                                "ƒ.ComponentMesh": {
                                                  "idMesh": "MeshCube|2022-02-13T09:02:24.853Z|43448",
                                                  "pivot": {
                                                    "translation": "[0, 0, 0]",
                                                    "rotation": "[0, 0, 0]",
                                                    "scaling": "[1, 1, 1]"
                                                  },
                                                  "Component": {
                                                    "active": true
                                                  }
                                                }
                                              }
                                            ],
                                            "ComponentMaterial": [
                                              {
                                                "ƒ.ComponentMaterial": {
                                                  "sortForAlpha": false,
                                                  "clrPrimary": "[1, 1, 1, 1]",
                                                  "clrSecondary": "[1, 1, 1, 1]",
                                                  "pivot": {
                                                    "translation": "[0, 0]",
                                                    "rotation": 0,
                                                    "scaling": "[1, 1]"
                                                  },
                                                  "Component": {
                                                    "active": true
                                                  },
                                                  "idMaterial": "Material|2022-02-13T09:02:43.900Z|50505"
                                                }
                                              }
                                            ],
                                            "ComponentTransform": [
                                              {
                                                "ƒ.ComponentTransform": {
                                                  "local": {
                                                    "translation": "[1, 2, 0]",
                                                    "rotation": "[0, 0, 0]",
                                                    "scaling": "[0.5, 0.5, 0.5]"
                                                  },
                                                  "Component": {
                                                    "active": true
                                                  }
                                                }
                                              }
                                            ],
                                            "ComponentRigidbody": [
                                              {
                                                "ƒ.ComponentRigidbody": {
                                                  "initialization": "TO_PIVOT",
                                                  "friction": 0.2,
                                                  "restitution": 0.2,
                                                  "mass": 1,
                                                  "dampTranslation": 0.1,
                                                  "dampRotation": 0.1,
                                                  "effectGravity": 1,
                                                  "typeBody": "DYNAMIC",
                                                  "typeCollider": "CUBE",
                                                  "isTrigger": false,
                                                  "id": 1,
                                                  "pivot": {
                                                    "translation": "[0, 0, 0]",
                                                    "rotation": "[0, 0, 0]",
                                                    "scaling": "[1, 1, 1]"
                                                  },
                                                  "Component": {
                                                    "active": true
                                                  }
                                                }
                                              }
                                            ]
                                          },
                                          "children": []
                                        }
                                      },
                                      {
                                        "ƒ.Node": {
                                          "name": "Obstacle3",
                                          "components": {
                                            "ComponentMesh": [
                                              {
                                                "ƒ.ComponentMesh": {
                                                  "idMesh": "MeshCube|2022-02-13T09:02:24.853Z|43448",
                                                  "pivot": {
                                                    "translation": "[0, 0, 0]",
                                                    "rotation": "[0, 0, 0]",
                                                    "scaling": "[1, 1, 1]"
                                                  },
                                                  "Component": {
                                                    "active": true
                                                  }
                                                }
                                              }
                                            ],
                                            "ComponentMaterial": [
                                              {
                                                "ƒ.ComponentMaterial": {
                                                  "sortForAlpha": false,
                                                  "clrPrimary": "[1, 1, 1, 1]",
                                                  "clrSecondary": "[1, 1, 1, 1]",
                                                  "pivot": {
                                                    "translation": "[0, 0]",
                                                    "rotation": 0,
                                                    "scaling": "[1, 1]"
                                                  },
                                                  "Component": {
                                                    "active": true
                                                  },
                                                  "idMaterial": "Material|2022-02-13T09:02:43.900Z|50505"
                                                }
                                              }
                                            ],
                                            "ComponentTransform": [
                                              {
                                                "ƒ.ComponentTransform": {
                                                  "local": {
                                                    "translation": "[2, 2, 0]",
                                                    "rotation": "[0, 0, 0]",
                                                    "scaling": "[0.5, 0.5, 0.5]"
                                                  },
                                                  "Component": {
                                                    "active": true
                                                  }
                                                }
                                              }
                                            ],
                                            "ComponentRigidbody": [
                                              {
                                                "ƒ.ComponentRigidbody": {
                                                  "initialization": "TO_PIVOT",
                                                  "friction": 0.2,
                                                  "restitution": 0.2,
                                                  "mass": 1,
                                                  "dampTranslation": 0.1,
                                                  "dampRotation": 0.1,
                                                  "effectGravity": 1,
                                                  "typeBody": "DYNAMIC",
                                                  "typeCollider": "CUBE",
                                                  "isTrigger": false,
                                                  "id": 1,
                                                  "pivot": {
                                                    "translation": "[0, 0, 0]",
                                                    "rotation": "[0, 0, 0]",
                                                    "scaling": "[1, 1, 1]"
                                                  },
                                                  "Component": {
                                                    "active": true
                                                  }
                                                }
                                              }
                                            ]
                                          },
                                          "children": []
                                        }
                                      }
                                    ]
                                  }
                                },
                                {
                                  "ƒ.Node": {
                                    "name": "Non-controllables",
                                    "components": {},
                                    "children": []
                                  }
                                }
                              ]
                            }
                          },
                          {
                            "ƒ.Node": {
                              "name": "Non-Movables",
                              "components": {},
                              "children": [
                                {
                                  "ƒ.Node": {
                                    "name": "Ground",
                                    "components": {},
                                    "children": [
                                      {
                                        "ƒ.Node": {
                                          "name": "left",
                                          "components": {
                                            "ComponentMesh": [
                                              {
                                                "ƒ.ComponentMesh": {
                                                  "idMesh": "MeshCube|2022-01-08T15:27:19.926Z|11492",
                                                  "pivot": {
                                                    "translation": "[0, 0, 0]",
                                                    "rotation": "[0, 0, 0]",
                                                    "scaling": "[8, 2, 1]"
                                                  },
                                                  "Component": {
                                                    "active": true
                                                  }
                                                }
                                              }
                                            ],
                                            "ComponentMaterial": [
                                              {
                                                "ƒ.ComponentMaterial": {
                                                  "sortForAlpha": false,
                                                  "clrPrimary": "[1, 1, 1, 1]",
                                                  "clrSecondary": "[1, 1, 1, 1]",
                                                  "pivot": {
                                                    "translation": "[0, 0]",
                                                    "rotation": 0,
                                                    "scaling": "[1, 1]"
                                                  },
                                                  "Component": {
                                                    "active": true
                                                  },
                                                  "idMaterial": "Material|2022-01-08T15:28:39.028Z|46109"
                                                }
                                              }
                                            ],
                                            "ComponentRigidbody": [
                                              {
                                                "ƒ.ComponentRigidbody": {
                                                  "initialization": "TO_MESH",
                                                  "friction": 0.2,
                                                  "restitution": 0.2,
                                                  "mass": 0,
                                                  "dampTranslation": 0.1,
                                                  "dampRotation": 0.1,
                                                  "effectGravity": 1,
                                                  "typeBody": "DYNAMIC",
                                                  "typeCollider": "CUBE",
                                                  "isTrigger": false,
                                                  "id": 0,
                                                  "pivot": {
                                                    "translation": "[0, 0, 0]",
                                                    "rotation": "[0, 0, 0]",
                                                    "scaling": "[8, 2, 1]"
                                                  },
                                                  "Component": {
                                                    "active": true
                                                  }
                                                }
                                              }
                                            ],
                                            "ComponentTransform": [
                                              {
                                                "ƒ.ComponentTransform": {
                                                  "local": {
                                                    "translation": "[0, 0, 0]",
                                                    "rotation": "[0, 0, 0]",
                                                    "scaling": "[1, 1, 1]"
                                                  },
                                                  "Component": {
                                                    "active": true
                                                  }
                                                }
                                              }
                                            ]
                                          },
                                          "children": []
                                        }
                                      },
                                      {
                                        "ƒ.Node": {
                                          "name": "right",
                                          "components": {
                                            "ComponentMesh": [
                                              {
                                                "ƒ.ComponentMesh": {
                                                  "idMesh": "MeshCube|2022-01-08T15:27:19.926Z|11492",
                                                  "pivot": {
                                                    "translation": "[10, 0, 0]",
                                                    "rotation": "[0, 0, 0]",
                                                    "scaling": "[6, 2, 1]"
                                                  },
                                                  "Component": {
                                                    "active": true
                                                  }
                                                }
                                              }
                                            ],
                                            "ComponentMaterial": [
                                              {
                                                "ƒ.ComponentMaterial": {
                                                  "sortForAlpha": false,
                                                  "clrPrimary": "[1, 1, 1, 1]",
                                                  "clrSecondary": "[1, 1, 1, 1]",
                                                  "pivot": {
                                                    "translation": "[0, 0]",
                                                    "rotation": 0,
                                                    "scaling": "[1, 1]"
                                                  },
                                                  "Component": {
                                                    "active": true
                                                  },
                                                  "idMaterial": "Material|2022-01-08T15:28:39.028Z|46109"
                                                }
                                              }
                                            ]
                                          },
                                          "children": []
                                        }
                                      },
                                      {
                                        "ƒ.Node": {
                                          "name": "2DBorder",
                                          "components": {},
                                          "children": [
                                            {
                                              "ƒ.Node": {
                                                "name": "Background",
                                                "components": {
                                                  "ComponentMesh": [
                                                    {
                                                      "ƒ.ComponentMesh": {
                                                        "idMesh": "MeshCube|2022-02-13T10:13:57.579Z|88727",
                                                        "pivot": {
                                                          "translation": "[0, 0, 0]",
                                                          "rotation": "[0, 0, 0]",
                                                          "scaling": "[1, 1, 0.10000000149011612]"
                                                        },
                                                        "Component": {
                                                          "active": true
                                                        }
                                                      }
                                                    }
                                                  ],
                                                  "ComponentMaterial": [
                                                    {
                                                      "ƒ.ComponentMaterial": {
                                                        "sortForAlpha": false,
                                                        "clrPrimary": "[1, 1, 1, 0]",
                                                        "clrSecondary": "[1, 1, 1, 0]",
                                                        "pivot": {
                                                          "translation": "[0, 0]",
                                                          "rotation": 0,
                                                          "scaling": "[1, 1]"
                                                        },
                                                        "Component": {
                                                          "active": true
                                                        },
                                                        "idMaterial": "Material|2022-02-13T10:14:56.909Z|82707"
                                                      }
                                                    }
                                                  ],
                                                  "ComponentRigidbody": [
                                                    {
                                                      "ƒ.ComponentRigidbody": {
                                                        "initialization": "TO_PIVOT",
                                                        "friction": 0.2,
                                                        "restitution": 0.2,
                                                        "mass": 100,
                                                        "dampTranslation": 0,
                                                        "dampRotation": 0,
                                                        "effectGravity": 0,
                                                        "typeBody": "STATIC",
                                                        "typeCollider": "CUBE",
                                                        "isTrigger": false,
                                                        "id": 2,
                                                        "pivot": {
                                                          "translation": "[0, 0, 0]",
                                                          "rotation": "[0, 0, 0]",
                                                          "scaling": "[1, 1, 1]"
                                                        },
                                                        "Component": {
                                                          "active": true
                                                        }
                                                      }
                                                    }
                                                  ],
                                                  "ComponentTransform": [
                                                    {
                                                      "ƒ.ComponentTransform": {
                                                        "local": {
                                                          "translation": "[0, 3.5300002098083496, -0.5]",
                                                          "rotation": "[0, 0, 0]",
                                                          "scaling": "[100, 5, 0.10000000149011612]"
                                                        },
                                                        "Component": {
                                                          "active": true
                                                        }
                                                      }
                                                    }
                                                  ]
                                                },
                                                "children": []
                                              }
                                            },
                                            {
                                              "ƒ.Node": {
                                                "name": "Foreground",
                                                "components": {
                                                  "ComponentMesh": [
                                                    {
                                                      "ƒ.ComponentMesh": {
                                                        "idMesh": "MeshCube|2022-02-13T10:13:57.579Z|88727",
                                                        "pivot": {
                                                          "translation": "[0, 0, 0]",
                                                          "rotation": "[0, 0, 0]",
                                                          "scaling": "[1, 1, 0.10000000149011612]"
                                                        },
                                                        "Component": {
                                                          "active": true
                                                        }
                                                      }
                                                    }
                                                  ],
                                                  "ComponentMaterial": [
                                                    {
                                                      "ƒ.ComponentMaterial": {
                                                        "sortForAlpha": false,
                                                        "clrPrimary": "[0.7647058823529411, 0.17254901960784313, 0.17254901960784313, 0]",
                                                        "clrSecondary": "[1, 1, 1, 0]",
                                                        "pivot": {
                                                          "translation": "[0, 0]",
                                                          "rotation": 0,
                                                          "scaling": "[1, 1]"
                                                        },
                                                        "Component": {
                                                          "active": true
                                                        },
                                                        "idMaterial": "Material|2022-02-13T10:14:56.909Z|82707"
                                                      }
                                                    }
                                                  ],
                                                  "ComponentRigidbody": [
                                                    {
                                                      "ƒ.ComponentRigidbody": {
                                                        "initialization": "TO_PIVOT",
                                                        "friction": 0.2,
                                                        "restitution": 0.2,
                                                        "mass": 100,
                                                        "dampTranslation": 0,
                                                        "dampRotation": 0,
                                                        "effectGravity": 0,
                                                        "typeBody": "STATIC",
                                                        "typeCollider": "CUBE",
                                                        "isTrigger": false,
                                                        "id": 2,
                                                        "pivot": {
                                                          "translation": "[0, 0, 0]",
                                                          "rotation": "[0, 0, 0]",
                                                          "scaling": "[1, 1, 1]"
                                                        },
                                                        "Component": {
                                                          "active": true
                                                        }
                                                      }
                                                    }
                                                  ],
                                                  "ComponentTransform": [
                                                    {
                                                      "ƒ.ComponentTransform": {
                                                        "local": {
                                                          "translation": "[0, 3.5300002098083496, 0.5]",
                                                          "rotation": "[0, 0, 0]",
                                                          "scaling": "[100, 5, 0.10000000149011612]"
                                                        },
                                                        "Component": {
                                                          "active": true
                                                        }
                                                      }
                                                    }
                                                  ]
                                                },
                                                "children": []
                                              }
                                            }
                                          ]
                                        }
                                      }
                                    ]
                                  }
                                },
                                {
                                  "ƒ.Node": {
                                    "name": "MovementBorder",
                                    "components": {},
                                    "children": []
                                  }
                                }
                              ]
                            }
                          }
                        ]
                      }
                    }
                  ]
                }
              },
              {
                "ƒ.Node": {
                  "name": "Sounds",
                  "components": {},
                  "children": [
                    {
                      "ƒ.Node": {
                        "name": "swosh",
                        "components": {
                          "ComponentAudio": [
                            {
                              "ƒ.ComponentAudio": {
                                "active": true,
                                "idResource": "Audio|2022-02-13T21:42:49.706Z|86540",
                                "playing": false,
                                "loop": false,
                                "volume": 1
                              }
                            }
                          ]
                        },
                        "children": []
                      }
                    }
                  ]
                }
              }
            ]
          }
        }
      ],
      "idResource": "Graph|2022-01-08T12:51:22.101Z|15244",
      "type": "Graph"
    }
  },
  "Audio|2022-02-13T21:42:49.706Z|86540": {
    "ƒ.Audio": {
      "url": "Sounds\\swosh.wav",
      "idResource": "Audio|2022-02-13T21:42:49.706Z|86540",
      "name": "Sounds\\swosh.wav",
      "type": "Audio"
    }
  }
}